porkbun_ddns/__init__.py
porkbun_ddns/cli.py
porkbun_ddns/config.py
porkbun_ddns/errors.py
porkbun_ddns/helpers.py
porkbun_ddns/porkbun_ddns.py
porkbun_ddns-1.1.21.dist-info/licenses/LICENSE
porkbun_ddns-1.1.21.dist-info/METADATA
porkbun_ddns-1.1.21.dist-info/WHEEL
porkbun_ddns-1.1.21.dist-info/entry_points.txt
porkbun_ddns-1.1.21.dist-info/top_level.txt
porkbun_ddns-1.1.21.dist-info/RECORD
