Metadata-Version: 2.4
Name: porkbun_ddns
Version: 1.1.21
Summary: A unofficial DDNS-Client for Porkbun domains
Author-email: Nils Stein <github.nstein@mailbox.org>
License: MIT License
Project-URL: repository, https://github.com/mietzen/porkbun-ddns
Keywords: porkbun,ddns
Classifier: Development Status :: 4 - Beta
Classifier: License :: OSI Approved :: MIT License
Classifier: Programming Language :: Python :: 3
Classifier: Operating System :: OS Independent
Requires-Python: >=3.10
License-File: LICENSE
Requires-Dist: xdg-base-dirs~=6.0.2
Dynamic: license-file
